certbot_dns_dnsprivacy/__init__.py
certbot_dns_dnsprivacy/dns_dnsprivacy.py
certbot_dns_dnsprivacy-0.4.0.dist-info/licenses/LICENSE
certbot_dns_dnsprivacy-0.4.0.dist-info/METADATA
certbot_dns_dnsprivacy-0.4.0.dist-info/WHEEL
certbot_dns_dnsprivacy-0.4.0.dist-info/entry_points.txt
certbot_dns_dnsprivacy-0.4.0.dist-info/top_level.txt
certbot_dns_dnsprivacy-0.4.0.dist-info/RECORD
