Metadata-Version: 2.4
Name: certbot-dns-dnsprivacy
Version: 0.4.0
Summary: Certbot DNS Plugin for the UK DNS Privacy Project
Author-email: Paul Trippett <support@dnsprivacy.org.uk>
License: MIT License
Project-URL: Homepage, https://dnsprivacy.org.uk/
Project-URL: Documentation, https://dnsprivacy.org.uk/docs/how-it-works/authoritative-dns.html
Project-URL: Donate, https://dnsprivacy.org.uk/support-us.html
Project-URL: Issues, https://github.com/UK-DNS-Privacy-Project/certbot-dns-dnsprivacy/issues
Project-URL: Mastodon, https://mastodonapp.uk/@ukdnsprivacyproject
Project-URL: Reddit, https://reddit.com/r/UKDNSPrivacyProject
Keywords: certbot,dns,letsencrypt
Classifier: Programming Language :: Python :: 3
Classifier: License :: OSI Approved :: MIT License
Classifier: Operating System :: OS Independent
License-File: LICENSE
Requires-Dist: certbot>=2.0.0
Requires-Dist: requests
Dynamic: license-file
